XenGarden/__init__.py
XenGarden/session.py
XenGarden/Common/__init__.py
XenGarden/Console/__init__.py
XenGarden/GuestMetrics/__init__.py
XenGarden/Host/__init__.py
XenGarden/Network/__init__.py
XenGarden/PIF/__init__.py
XenGarden/SR/__init__.py
XenGarden/VBD/__init__.py
XenGarden/VDI/__init__.py
XenGarden/VIF/__init__.py
XenGarden/VM/__init__.py
XenGarden-1.2.13.dist-info/LICENSE
XenGarden-1.2.13.dist-info/METADATA
XenGarden-1.2.13.dist-info/WHEEL
XenGarden-1.2.13.dist-info/top_level.txt
XenGarden-1.2.13.dist-info/RECORD
