Metadata-Version: 2.1
Name: XenGarden
Version: 1.2.13
Summary: XenGarden, A Python XenAPI Wrapper for Citrix Hypervisor and XCP-ng Servers
Home-page: https://github.com/Stella-IT/XenGarden
Author: Stella IT
Author-email: contact@stella-it.com
License: UNKNOWN
Keywords: XenGarden,XenAPI,XenAPI Wrapper,Citrix Hypervisor,XCP-ng
Platform: UNKNOWN
Classifier: Programming Language :: Python :: 3.7
Classifier: Programming Language :: Python :: 3.8
Requires-Python: >=3
Requires-Dist: xenapi
Requires-Dist: deprecated
